navipy/__init__.py
navipy/scene.py
navipy/arenatools/__init__.py
navipy/arenatools/cam_calib.py
navipy/arenatools/cam_dlt.py
navipy/arenatools/patterns.py
navipy/arenatools/triangulate.py
navipy/comparing/__init__.py
navipy/comparing/test.py
navipy/database/__init__.py
navipy/database/test.py
navipy/database/tools.py
navipy/errorprop/__init__.py
navipy/errorprop/test.py
navipy/io/__init__.py
navipy/io/ivfile.py
navipy/io/opencv.py
navipy/maths/__init__.py
navipy/maths/constants.py
navipy/maths/coordinates.py
navipy/maths/euler.py
navipy/maths/homogeneous_transformations.py
navipy/maths/quaternion.py
navipy/maths/random.py
navipy/maths/test_euler.py
navipy/maths/test_homogeneous_transformations.py
navipy/maths/test_quaternion.py
navipy/maths/test_random.py
navipy/maths/tools.py
navipy/models/__init__.py
navipy/models/dewar_2014.py
navipy/models/hafner_2000.py
navipy/models/irdf_2003.py
navipy/moving/__init__.py
navipy/moving/agent.py
navipy/moving/maths.py
navipy/moving/test_agent.py
navipy/moving/test_maths.py
navipy/processing/__init__.py
navipy/processing/mcode.py
navipy/processing/pcode.py
navipy/processing/test.py
navipy/processing/test_OpticFlow.py
navipy/processing/test_mcode.py
navipy/processing/test_opticflow.py
navipy/resources/database.db
navipy/resources/database2.db
navipy/resources/forest_world.blend
navipy/resources/twocylinders_world.blend
navipy/resources/configs/BlenderOnGridRender.yaml
navipy/resources/configs/BlenderRender.yaml
navipy/resources/sample_experiment/Doussot_2017/bee007.hdf
navipy/resources/sample_experiment/Doussot_2018a/20180117_cam_0.tif
navipy/resources/sample_experiment/Doussot_2018a/20180117_cam_2.tif
navipy/resources/sample_experiment/Doussot_2018a/bee_005_cam_0_bodyxypts.csv
navipy/resources/sample_experiment/Doussot_2018a/bee_005_cam_2_bodyxypts.csv
navipy/resources/sample_experiment/Doussot_2018a/bodybee05.hdf
navipy-0.1.dist-info/DESCRIPTION.rst
navipy-0.1.dist-info/METADATA
navipy-0.1.dist-info/RECORD
navipy-0.1.dist-info/WHEEL
navipy-0.1.dist-info/entry_points.txt
navipy-0.1.dist-info/metadata.json
navipy-0.1.dist-info/top_level.txt
